gbpui/_1550_gbp_project_add_panel_group.py
gbpui/_1560_gbp_project_add_panel.py
gbpui/_1561_gbp_project_add_panel.py
gbpui/_1562_gbp_project_add_panel.py
gbpui/_1563_gbp_project_add_panel.py
gbpui/__init__.py
gbpui/client.py
gbpui/column_filters.py
gbpui/fields.py
gbpui/panel_group.py
gbpui/horizon/__init__.py
gbpui/horizon/tests/__init__.py
gbpui/horizon/tests/base.py
gbpui/horizon/tests/test_gbpui.py
gbpui/openstack_dashboard/__init__.py
gbpui/openstack_dashboard/tests/__init__.py
gbpui/openstack_dashboard/tests/base.py
gbpui/openstack_dashboard/tests/test_gbpui.py
gbpui/panels/__init__.py
gbpui/panels/application_policy/__init__.py
gbpui/panels/application_policy/forms.py
gbpui/panels/application_policy/panel.py
gbpui/panels/application_policy/tables.py
gbpui/panels/application_policy/tabs.py
gbpui/panels/application_policy/urls.py
gbpui/panels/application_policy/views.py
gbpui/panels/application_policy/workflows.py
gbpui/panels/application_policy/templates/application_policy/_add_policy_action.html
gbpui/panels/application_policy/templates/application_policy/_add_policy_classifier.html
gbpui/panels/application_policy/templates/application_policy/_policy_rule_set_details.html
gbpui/panels/application_policy/templates/application_policy/_policyaction_details.html
gbpui/panels/application_policy/templates/application_policy/_policyclassifier_details.html
gbpui/panels/application_policy/templates/application_policy/_policyrules_details.html
gbpui/panels/application_policy/templates/application_policy/_update_policy_action.html
gbpui/panels/application_policy/templates/application_policy/_update_policy_classifier.html
gbpui/panels/application_policy/templates/application_policy/_update_policy_rule.html
gbpui/panels/application_policy/templates/application_policy/_update_policy_rule_set.html
gbpui/panels/application_policy/templates/application_policy/addpolicy_rule_set.html
group_based_policy_ui-2015.2.5.dist-info/DESCRIPTION.rst
group_based_policy_ui-2015.2.5.dist-info/METADATA
group_based_policy_ui-2015.2.5.dist-info/RECORD
group_based_policy_ui-2015.2.5.dist-info/WHEEL
group_based_policy_ui-2015.2.5.dist-info/metadata.json
group_based_policy_ui-2015.2.5.dist-info/pbr.json
group_based_policy_ui-2015.2.5.dist-info/top_level.txt
